LICENSE
README.md
setup.py
cgai_path/__init__.py
cgai_path/cpath.py
cgai_path.egg-info/PKG-INFO
cgai_path.egg-info/SOURCES.txt
cgai_path.egg-info/dependency_links.txt
cgai_path.egg-info/top_level.txt